cd_network/__init__.py
cd_network/cells.py
cd_network/coincidence_integral.py
cd_network/network.py
cd_network/run.py
cd_network/utils.py
cd_network/version.py
cd_network-0.1.4.dist-info/LICENSE
cd_network-0.1.4.dist-info/METADATA
cd_network-0.1.4.dist-info/WHEEL
cd_network-0.1.4.dist-info/entry_points.txt
cd_network-0.1.4.dist-info/top_level.txt
cd_network-0.1.4.dist-info/RECORD
