Metadata-Version: 2.1
Name: cd_network
Version: 0.1.4
Summary: A framework designed to calculate the output of neurons based on non-homogeneous Poisson processes and rate statistic calculations
Home-page: https://github.com/nuniz/CoincidenceDetectionNetwork
Author: Asaf Zorea
Author-email: zoreasaf@gmail.com
License: MIT
Project-URL: Bug Tracker, https://github.com/nuniz/CoincidenceDetectionNetwork/issues
Classifier: Programming Language :: Python :: 3
Classifier: License :: OSI Approved :: MIT License
Classifier: Operating System :: OS Independent
Classifier: Development Status :: 3 - Alpha
Classifier: Intended Audience :: Science/Research
Classifier: Topic :: Scientific/Engineering :: Bio-Informatics
Requires-Python: >=3.6
License-File: LICENSE
Requires-Dist: numpy <2
Requires-Dist: scipy
Requires-Dist: matplotlib
Requires-Dist: networkx
Provides-Extra: dev
Requires-Dist: pytest ; extra == 'dev'
Requires-Dist: check-manifest ; extra == 'dev'
Requires-Dist: pre-commit ; extra == 'dev'
Provides-Extra: test
Requires-Dist: pytest ; extra == 'test'
Requires-Dist: coverage ; extra == 'test'
